{
  "name": "k8s-kind-dev",
  "build": {
    "dockerfile": "Dockerfile",
    "context": "."
  },
  "features": {
    "ghcr.io/devcontainers/features/docker-outside-of-docker:1": {},
    "ghcr.io/devcontainers/features/sshd:1": {
        "version": "latest"
    }
  },
  "runArgs": [
    "--network=host",
    "--add-host=host.docker.internal:host-gateway"
  ],
  "mounts": [
    "source=/var/run/docker.sock,target=/var/run/docker.sock,type=bind"
  ],
  "hostRequirements": {
    "cpus": 4,
    "memory": "16gb",
    "storage": "32gb"
  },
  "containerEnv": {
    "KUBECONFIG": "/workspaces/.kube/dev.yaml",
  },
  "postStartCommand": "/bin/bash -lc '_scripts/start.sh'",
  "customizations": {
    "vscode": {
      "extensions": ["ms-kubernetes-tools.vscode-kubernetes-tools"]
    }
  },
  "forwardPorts": [
    8080,
    3000,
    8181
  ],
  "portsAttributes": {
    "8080": {
      "label": "WebUI"
    },
    "3000": {
      "label": "Grafana"
    },
    "8181": {
      "label": "WebUI for Standby"
    }
  },
  "remoteEnv": {
    "DOCKER_API_VERSION": "1.43"
  }
}